tyz_library
