Metadata-Version: 1.1
Name: tyz-library
Version: 1.0.8
Summary: this is a test package for packing python liberaries tutorial.
Home-page: http://blog.useasp.net/
Author: tianyunzi
Author-email: 854024109@qq.com
License: MIT
Keywords: test python package
Platform: UNKNOWN
Classifier: License :: OSI Approved :: MIT License
Classifier: Programming Language :: Python
Classifier: Intended Audience :: Developers
Classifier: Operating System :: OS Independent
